drain3/__init__.py
drain3/drain.py
drain3/file_persistence.py
drain3/jaccard_drain.py
drain3/kafka_persistence.py
drain3/masking.py
drain3/memory_buffer_persistence.py
drain3/persistence_handler.py
drain3/redis_persistence.py
drain3/simple_profiler.py
drain3/template_miner.py
drain3/template_miner_config.py
drain3_ankcorn-0.9.14.dist-info/LICENSE.txt
drain3_ankcorn-0.9.14.dist-info/METADATA
drain3_ankcorn-0.9.14.dist-info/WHEEL
drain3_ankcorn-0.9.14.dist-info/RECORD
