Metadata-Version: 2.1
Name: drain3-ankcorn
Version: 0.9.14
Summary: Persistent & streaming log template miner
License: MIT
Keywords: drain,log,parser,IBM,template,logs,miner
Author: IBM Research Haifa
Author-email: david.ohana@ibm.com
Maintainer: Yihao Chen(Superskyyy)
Maintainer-email: yihaochen@apache.org
Requires-Python: >=3.7,<4.0
Classifier: License :: OSI Approved :: MIT License
Classifier: Operating System :: OS Independent
Classifier: Programming Language :: Python :: 3
Classifier: Programming Language :: Python :: 3.7
Classifier: Programming Language :: Python :: 3.8
Classifier: Programming Language :: Python :: 3.9
Classifier: Programming Language :: Python :: 3.10
Classifier: Programming Language :: Python :: 3.11
Classifier: Programming Language :: Python :: 3.12
Classifier: Topic :: Software Development :: Libraries
Classifier: Topic :: System :: Monitoring
Provides-Extra: all
Provides-Extra: kafka
Provides-Extra: redis
Requires-Dist: cachetools
Requires-Dist: jsonpickle
Requires-Dist: kafka-python ; extra == "all" or extra == "kafka"
Requires-Dist: redis ; extra == "all" or extra == "redis"
